ddf/DirtyDF.py
ddf/__init__.py
ddf/history.py
ddf/latlong.py
ddf/samplers.py
ddf/stainer.py
dirtydf-0.0.22.dist-info/LICENSE
dirtydf-0.0.22.dist-info/METADATA
dirtydf-0.0.22.dist-info/WHEEL
dirtydf-0.0.22.dist-info/top_level.txt
dirtydf-0.0.22.dist-info/RECORD
